README.md
setup.py
dog_whistle/__init__.py
dog_whistle/__version__.py
dog_whistle.egg-info/PKG-INFO
dog_whistle.egg-info/SOURCES.txt
dog_whistle.egg-info/dependency_links.txt
dog_whistle.egg-info/requires.txt
dog_whistle.egg-info/top_level.txt
dog_whistle.egg-info/zip-safe